thriftasyncioserver/__init__.py
thriftasyncioserver-0.1.7.dist-info/dependency_links.txt
thriftasyncioserver-0.1.7.dist-info/DESCRIPTION.rst
thriftasyncioserver-0.1.7.dist-info/METADATA
thriftasyncioserver-0.1.7.dist-info/metadata.json
thriftasyncioserver-0.1.7.dist-info/RECORD
thriftasyncioserver-0.1.7.dist-info/top_level.txt
thriftasyncioserver-0.1.7.dist-info/WHEEL
thriftasyncioserver-0.1.7.dist-info/zip-safe
