Metadata-Version: 2.0
Name: thriftasyncioserver
Version: 0.1.7
Summary: Thrift Server using the Python 3 asyncio module
Home-page: https://github.com/Marketcircle/thriftasyncioserver
Author: Thomas Bartelmess
Author-email: tbartelmess@marketcircle.com
License: BSD
Keywords: thriftasyncioserver
Platform: UNKNOWN
Classifier: Development Status :: 2 - Pre-Alpha
Classifier: Intended Audience :: Developers
Classifier: License :: OSI Approved :: BSD License
Classifier: Natural Language :: English
Classifier: Programming Language :: Python :: 3.4
Requires-Dist: thrift
